arguments/__init__.py
arguments/api.py
tombulled_arguments-0.1.5.dist-info/LICENSE
tombulled_arguments-0.1.5.dist-info/WHEEL
tombulled_arguments-0.1.5.dist-info/METADATA
tombulled_arguments-0.1.5.dist-info/RECORD
